redshift_connection/__init__.py
redshift_connection/provider.py
tests/__init__.py
tests/test_redshift_connection.py
redshift_connection_provider-0.5.0b2.dist-info/LICENSE
redshift_connection_provider-0.5.0b2.dist-info/METADATA
redshift_connection_provider-0.5.0b2.dist-info/WHEEL
redshift_connection_provider-0.5.0b2.dist-info/top_level.txt
redshift_connection_provider-0.5.0b2.dist-info/RECORD
