Metadata-Version: 2.1
Name: redshift-connection-provider
Version: 0.5.0b2
Summary: An opinionated class to retrieve a Redshift connection object compatible with psycopg2.
Home-page: https://github.com/dreamorosi/redshift-connection-provider
Author: Andrea Amorosi
License: UNKNOWN
Platform: UNKNOWN
Classifier: Development Status :: 4 - Beta
Classifier: Intended Audience :: Developers
Classifier: License :: OSI Approved :: MIT License
Classifier: Programming Language :: Python :: 3 :: Only
Classifier: Programming Language :: Python :: 3.7
Classifier: Programming Language :: Python :: 3.8
Classifier: Topic :: Utilities
Classifier: Typing :: Typed
Requires-Python: >=3.7
Requires-Dist: boto3 (~=1.16.57)
